dpet/__init__.py
dpet/dimensionality_reduction.py
dpet/ensemble.py
dpet/ensemble_analysis.py
dpet/visualization.py
dpet/data/__init__.py
dpet/data/api_client.py
dpet/data/comparison.py
dpet/data/coord.py
dpet/data/extract_tar_gz.py
dpet/data/topology.py
dpet/featurization/__init__.py
dpet/featurization/angles.py
dpet/featurization/distances.py
dpet/featurization/ensemble_level.py
dpet/featurization/glob.py
dpet/featurization/utils.py
dpet-1.0.2.dist-info/METADATA
dpet-1.0.2.dist-info/WHEEL
dpet-1.0.2.dist-info/top_level.txt
dpet-1.0.2.dist-info/RECORD
